{
  "label": "attr-marginal-mixture",
  "name": "Marginal as Mixture Average",
  "statement_type": "proposition",
  "source": null,
  "input_objects": [
    "obj-qsd",
    "obj-single-particle-marginal"
  ],
  "input_axioms": [],
  "input_parameters": [
    "param-N"
  ],
  "attributes_required": {
    "obj-qsd": [
      "attr-de-finetti-mixture"
    ]
  },
  "internal_lemmas": [],
  "internal_propositions": [],
  "lemma_dag_edges": [],
  "output_type": "Property",
  "attributes_added": [
    {
      "label": "attr-marginal-mixture-average",
      "expression": "\u03bc_N = \u222b \u03bc d\ud835\udcac_N(\u03bc)",
      "object_label": "obj-single-particle-marginal"
    }
  ],
  "relations_established": []
}