{
  "label": "thm-hewitt-savage-representation",
  "name": "Mixture Representation (Hewitt-Savage)",
  "statement_type": "theorem",
  "source": null,
  "input_objects": [
    "obj-qsd"
  ],
  "input_axioms": [],
  "input_parameters": [
    "param-N"
  ],
  "attributes_required": {
    "obj-qsd": [
      "attr-exchangeability"
    ]
  },
  "internal_lemmas": [],
  "internal_propositions": [],
  "lemma_dag_edges": [],
  "output_type": "Existence",
  "attributes_added": [
    {
      "label": "attr-de-finetti-mixture",
      "expression": "\u03c0_N = \u222b \u03bc^{\u2297N} d\ud835\udcac_N(\u03bc)",
      "object_label": "obj-qsd"
    }
  ],
  "relations_established": []
}