{
  "label": "obj-cloning-decision",
  "name": "The Stochastic Cloning Decision",
  "mathematical_expression": "S_i(c_i)",
  "object_type": "distribution",
  "current_attributes": [],
  "attribute_history": [],
  "tags": [
    "particle"
  ],
  "source": {
    "document_id": "03_cloning",
    "file_path": "/home/guillem/fragile/docs/source/1_euclidean_gas/03_cloning.md",
    "section": null,
    "directive_label": "obj-cloning-decision",
    "equation": null,
    "line_range": null,
    "url_fragment": "#obj-cloning-decision"
  },
  "chapter": null,
  "document": null,
  "definition_label": null
}