{
  "label": "thm-deterministic-potential-continuity",
  "label_text": "Deterministic Continuity of the Fitness Potential Operator",
  "statement_type": "theorem",
  "full_statement_text": "Let the Fitness Potential Operator $V_{\\text{op}}$ be constructed using the patched **N-Dimensional Standardization Operator**. Let $(\\mathcal{S}_1, \\mathbf{v}_{r1}, \\mathbf{v}_{d1})$ and $(\\mathcal{S}_2, \\mathbf{v}_{r2}, \\mathbf{v}_{d2})$ be two sets of inputs, consisting of swarm states and their corresponding raw reward and distance vectors. Let $\\mathbf{V}_1$ and $\\mathbf{V}_2$ be the resulting N-dimensional fitness potential vectors.\nThe squared Euclidean error between the output potential vectors is deterministically bounded by a function of the swarm displacement and the raw value differences:\n$$\n\n\\|\\mathbf{V}_1 - \\mathbf{V}_2\\|_2^2 \\le F_{\\text{pot,det}}(\\mathcal{S}_1, \\mathcal{S}_2, \\mathbf{v}_{r1}, \\mathbf{v}_{r2}, \\mathbf{v}_{d1}, \\mathbf{v}_{d2})\n\n$$\nwhere $F_{\\text{pot,det}}$ is a deterministic bounding function that is jointly continuous in its arguments and vanishes as $d_{\\text{Disp},\\mathcal{Y}}(\\mathcal{S}_1, \\mathcal{S}_2) \\to 0$, $\\|\\mathbf{v}_{r1} - \\mathbf{v}_{r2}\\|_2 \\to 0$, and $\\|\\mathbf{v}_{d1} - \\mathbf{v}_{d2}\\|_2 \\to 0$.",
  "input_objects": [],
  "input_axioms": [],
  "input_parameters": [],
  "output_type": "Bound",
  "relations_established": [],
  "source": {
    "document_id": "01_fragile_gas_framework",
    "file_path": "docs/source/1_euclidean_gas/01_fragile_gas_framework.md",
    "chapter": "1_euclidean_gas",
    "section": null,
    "section_name": null,
    "label": "thm-deterministic-potential-continuity",
    "line_range": {
      "lines": [
        [
          3890,
          3899
        ]
      ]
    },
    "equation": null,
    "url_fragment": null
  }
}